GNS3Utils/GNS3Utils.py
GNS3Utils/__init__.py
GNS3Utils-1.1.0.dist-info/LICENSE
GNS3Utils-1.1.0.dist-info/METADATA
GNS3Utils-1.1.0.dist-info/WHEEL
GNS3Utils-1.1.0.dist-info/top_level.txt
GNS3Utils-1.1.0.dist-info/RECORD
