Metadata-Version: 2.1
Name: GNS3Utils
Version: 1.1.0
Summary: This project can help you with GNS3 automation
Home-page: https://github.com/Belyashik-code/GNS3Utils
Author: Beliaev Aleksandr
Author-email: belyaevaleksandr@icloud.com
Project-URL: Documentation, https://github.com/Belyashik-code/GNS3Utils
Keywords: gns3 GNS3 GNS3API
Classifier: Programming Language :: Python :: 3.11
Classifier: License :: OSI Approved :: MIT License
Classifier: Operating System :: OS Independent
Requires-Python: >=3.7
License-File: LICENSE
Requires-Dist: requests>=2.25.1
